pygiftparser/__init__.py
pygiftparser/gift.py
pygiftparser/parser.py
pygiftparser/preprocessor.py
tests/__init__.py
tests/test_all_questions.py
tests/test_all_questions_categories.py
tests/test_description.py
tests/test_escaping.py
tests/test_essay.py
tests/test_matching.py
tests/test_multiple_choice_checkbox.py
tests/test_multiple_choice_radio.py
tests/test_numerical.py
tests/test_numerical_multiple.py
tests/test_numerical_range.py
tests/test_short.py
tests/test_truefalse.py
pygiftparserrgmf-0.0.5.dist-info/LICENSE
pygiftparserrgmf-0.0.5.dist-info/METADATA
pygiftparserrgmf-0.0.5.dist-info/WHEEL
pygiftparserrgmf-0.0.5.dist-info/top_level.txt
pygiftparserrgmf-0.0.5.dist-info/RECORD
