Metadata-Version: 2.1
Name: pygiftparserrgmf
Version: 0.0.5
Summary: Moodle GIFT files parser
Home-page: https://github.com/rgmf/pygiftparser
Author: Román Martínez
Author-email: rgmf@riseup.net
License: UNKNOWN
Platform: UNKNOWN
Classifier: Programming Language :: Python :: 3
Classifier: License :: OSI Approved :: GNU Affero General Public License v3
Classifier: Operating System :: POSIX :: Linux
Requires-Python: >=3.8
Requires-Dist: ply
